pvpltools/__init__.py
pvpltools/dataplusmeta.py
pvpltools/iec61853.py
pvpltools/module_efficiency.py
pvpltools/power_conversion.py
pvpltools/version.py
pvpltools/data/climate_profiles/readme.md
pvpltools/data/nrel_mpert/readme.md
pvpltools/data/nrel_mpert/modules/CIGS1-001.txt
pvpltools/data/nrel_mpert/modules/CIGS39013.txt
pvpltools/data/nrel_mpert/modules/CIGS39017.txt
pvpltools/data/nrel_mpert/modules/CIGS8-001.txt
pvpltools/data/nrel_mpert/modules/CdTe75638.txt
pvpltools/data/nrel_mpert/modules/CdTe75669.txt
pvpltools/data/nrel_mpert/modules/HIT05662.txt
pvpltools/data/nrel_mpert/modules/HIT05667.txt
pvpltools/data/nrel_mpert/modules/aSiTandem72-46.txt
pvpltools/data/nrel_mpert/modules/aSiTandem90-31.txt
pvpltools/data/nrel_mpert/modules/aSiTriple28324.txt
pvpltools/data/nrel_mpert/modules/aSiTriple28325.txt
pvpltools/data/nrel_mpert/modules/mSi0166.txt
pvpltools/data/nrel_mpert/modules/mSi0188.txt
pvpltools/data/nrel_mpert/modules/mSi0247.txt
pvpltools/data/nrel_mpert/modules/mSi0251.txt
pvpltools/data/nrel_mpert/modules/mSi460A8.txt
pvpltools/data/nrel_mpert/modules/mSi460BB.txt
pvpltools/data/nrel_mpert/modules/xSi11246.txt
pvpltools/data/nrel_mpert/modules/xSi12922.txt
pvpltools/test/test_dataplusmeta.py
pvpltools/test/test_iec61853.py
pvpltools/test/data/.gitignore
pvpltools/test/data/sample_iec.txt
pvpltools-0.1.0.dist-info/LICENSE
pvpltools-0.1.0.dist-info/METADATA
pvpltools-0.1.0.dist-info/WHEEL
pvpltools-0.1.0.dist-info/top_level.txt
pvpltools-0.1.0.dist-info/RECORD
